firebase_admin/__about__.pyi
firebase_admin/__init__.pyi
firebase_admin/_auth_client.pyi
firebase_admin/_auth_providers.pyi
firebase_admin/_auth_utils.pyi
firebase_admin/_gapic_utils.pyi
firebase_admin/_http_client.pyi
firebase_admin/_messaging_encoder.pyi
firebase_admin/_messaging_utils.pyi
firebase_admin/_rfc3339.pyi
firebase_admin/_sseclient.pyi
firebase_admin/_token_gen.pyi
firebase_admin/_user_identifier.pyi
firebase_admin/_user_import.pyi
firebase_admin/_user_mgt.pyi
firebase_admin/_utils.pyi
firebase_admin/app_check.pyi
firebase_admin/auth.pyi
firebase_admin/credentials.pyi
firebase_admin/db.pyi
firebase_admin/exceptions.pyi
firebase_admin/firestore.pyi
firebase_admin/firestore_async.pyi
firebase_admin/functions.pyi
firebase_admin/instance_id.pyi
firebase_admin/messaging.pyi
firebase_admin/ml.pyi
firebase_admin/project_management.pyi
firebase_admin/storage.pyi
firebase_admin/tenant_mgt.pyi
google/cloud/firestore_v1/__init__.pyi
google/cloud/firestore_v1/client.pyi
google/cloud/firestore_v1/document.pyi
google/cloud/firestore_v1/query.pyi
firebase_admin/py.typed
types_firebase_admin-0.1.1.dist-info/METADATA
types_firebase_admin-0.1.1.dist-info/WHEEL
types_firebase_admin-0.1.1.dist-info/licenses/LICENSE
types_firebase_admin-0.1.1.dist-info/RECORD
